mammos_analysis/__init__.py
mammos_analysis/hysteresis.py
mammos_analysis/kuzmin.py
mammos_analysis/py.typed
mammos_analysis-0.4.0.dist-info/METADATA
mammos_analysis-0.4.0.dist-info/WHEEL
mammos_analysis-0.4.0.dist-info/licenses/LICENSE
mammos_analysis-0.4.0.dist-info/RECORD
