Metadata-Version: 2.4
Name: mammos-analysis
Version: 0.4.0
Summary: Analysis functionality package.
Project-URL: Homepage, https://MaMMoS-project.github.io
Project-URL: Documentation, https://mammos-project.github.io/mammos
Project-URL: Repository, https://github.com/MaMMoS-project/mammos-analysis
Project-URL: Issues, https://github.com/MaMMoS-project/mammos-analysis/issues
Project-URL: Changelog, https://mammos-project.github.io/mammos/changelog
Author: Andrea Petrocchi, Swapneel Amit Pathak, Martin Lang, Samuel Holt, Hans Fangohr
License-Expression: MIT
License-File: LICENSE
Classifier: Intended Audience :: Developers
Classifier: Intended Audience :: Education
Classifier: Intended Audience :: Science/Research
Classifier: Programming Language :: Python :: 3 :: Only
Classifier: Topic :: Scientific/Engineering :: Physics
Requires-Python: >=3.11
Requires-Dist: mammos-entity>=0.8.0
Requires-Dist: mammos-units
Requires-Dist: matplotlib
Requires-Dist: numpy
Requires-Dist: pydantic
Requires-Dist: scipy
